py_logex/__init__.py
py_logex/cli.py
py_logex/config.py
py_logex/defaults.py
py_logex/exceptions.py
py_logex/logger.py
py_logex/utils.py
py_logex_enhanced-0.1.4.dist-info/licenses/LICENSE
py_logex_enhanced-0.1.4.dist-info/METADATA
py_logex_enhanced-0.1.4.dist-info/WHEEL
py_logex_enhanced-0.1.4.dist-info/entry_points.txt
py_logex_enhanced-0.1.4.dist-info/top_level.txt
py_logex_enhanced-0.1.4.dist-info/RECORD
