Metadata-Version: 2.4
Name: py-logex-enhanced
Version: 0.1.4
Summary: Simple, powerful logging with built-in exception handling and YAML configuration
Author-email: SherozShaikh <shaikh.sheroz07@gmail.com>
License: MIT License
Project-URL: Homepage, https://github.com/sherozshaikh/py-logex
Project-URL: Documentation, https://github.com/sherozshaikh/py-logex#readme
Project-URL: Repository, https://github.com/sherozshaikh/py-logex
Project-URL: Bug Tracker, https://github.com/sherozshaikh/py-logex/issues
Keywords: logging,logger,loguru,exception,yaml,configuration
Classifier: Development Status :: 4 - Beta
Classifier: Intended Audience :: Developers
Classifier: Programming Language :: Python :: 3
Classifier: Programming Language :: Python :: 3.8
Classifier: Programming Language :: Python :: 3.9
Classifier: Programming Language :: Python :: 3.10
Classifier: Programming Language :: Python :: 3.11
Classifier: Programming Language :: Python :: 3.12
Classifier: Topic :: Software Development :: Libraries :: Python Modules
Classifier: Topic :: System :: Logging
Requires-Python: >=3.8
License-File: LICENSE
Requires-Dist: loguru>=0.7.0
Requires-Dist: pyyaml>=6.0
Provides-Extra: dev
Requires-Dist: pytest>=7.0.0; extra == "dev"
Requires-Dist: pytest-cov>=4.0.0; extra == "dev"
Requires-Dist: black>=23.0.0; extra == "dev"
Requires-Dist: flake8>=6.0.0; extra == "dev"
Requires-Dist: mypy>=1.0.0; extra == "dev"
Dynamic: license-file
